{
  "personaId": "P013",
  "personaName": "오현우",
  "department": "R&D",
  "digitalMaturity": "Expert",
  "startTime": "2025-11-23T03:56:23.964Z",
  "endTime": "2025-11-23T03:59:06.968Z",
  "totalDuration": 163,
  "stageResults": [
    {
      "stageNumber": 1,
      "stageName": "워크샵 시작",
      "actualMinutes": 7,
      "timePerception": "Just Right",
      "easeOfUse": 6,
      "clarity": 5,
      "value": 7,
      "painPoints": [
        "연구 프로젝트의 복잡한 실험 단계와 기술 개발 프로세스를 단순화하기 어려움",
        "세부 기술적 맥락을 충분히 반영하지 못하는 제너럴한 인터페이스",
        "정량적/정성적 데이터의 상세 입력 한계"
      ],
      "positivePoints": [
        "팀 전체 업무 흐름을 시각화할 수 있는 가능성",
        "R&D 프로젝트 전체 로드맵 간략하게 정리 가능",
        "팀원 간 업무 분배와 진행 상황 공유에 잠재력"
      ],
      "suggestions": [
        "기술 연구 특화된 세부 워크플로우 템플릿 추가",
        "실험 단계별 상세 데이터 입력 기능 개발",
        "기술적 KPI와 연구 성과 추적 기능 고도화"
      ],
      "wouldContinue": true,
      "emotionalState": "Cautiously Optimistic"
    },
    {
      "stageNumber": 2,
      "stageName": "미션 작성",
      "actualMinutes": 8,
      "timePerception": "Just Right",
      "easeOfUse": 6,
      "clarity": 5,
      "value": 7,
      "painPoints": [
        "복잡한 실험 단계와 기술 개발 프로세스의 세부 사항 입력 제한",
        "정량적/정성적 연구 데이터의 상세 캡처 어려움",
        "기술적 맥락의 깊이 있는 표현 부족"
      ],
      "positivePoints": [
        "프로젝트 전체 구조화 가능성",
        "팀 목표 시각화 기능",
        "업무 흐름의 거시적 관점 제공"
      ],
      "suggestions": [
        "R&D 특화 워크플로우 템플릿 추가",
        "실험 단계별 세부 메트릭스 입력 기능",
        "기술적 복잡성을 반영하는 고급 입력 옵션",
        "연구 프로젝트 특화 KPI 트래킹 기능"
      ],
      "wouldContinue": true,
      "emotionalState": "Cautiously Optimistic"
    },
    {
      "stageNumber": 3,
      "stageName": "팀 상황 확인",
      "actualMinutes": 9,
      "timePerception": "Just Right",
      "easeOfUse": 6,
      "clarity": 5,
      "value": 7,
      "painPoints": [
        "복잡한 R&D 실험 프로세스의 세부 단계 입력 제한",
        "기술적 맥락과 연구 데이터의 심층적 캡처 어려움",
        "다양한 실험 변수와 기술 개발 세부사항 반영 부족"
      ],
      "positivePoints": [
        "팀 업무 구조화를 위한 기본 프레임워크 제공",
        "연구 프로젝트 전반적 흐름 시각화 가능",
        "팀 업무 프로세스 간략한 매핑 기능"
      ],
      "suggestions": [
        "R&D 특화된 상세 실험 단계 입력 기능 추가",
        "기술적 데이터 및 연구 변수 세부 입력 필드 개발",
        "실험 프로토콜 및 기술 개발 세부 프로세스 맞춤 템플릿 제공",
        "정량/정성 데이터 복합 분석 인터페이스 개선"
      ],
      "wouldContinue": true,
      "emotionalState": "Cautiously Interested"
    },
    {
      "stageNumber": 4,
      "stageName": "업무 영역 정의",
      "actualMinutes": 6,
      "timePerception": "Just Right",
      "easeOfUse": 5,
      "clarity": 4,
      "value": 6,
      "painPoints": [
        "복잡한 실험 프로토콜의 세부 단계 캡처 제한",
        "기술 개발 과정의 정량적/정성적 데이터 상세 입력 어려움",
        "연구 변수와 기술적 맥락의 심층적 표현 부족",
        "다양한 실험 단계와 연구 프로세스의 정밀한 매핑 미흡"
      ],
      "positivePoints": [
        "대략적인 업무 영역 구조화 가능",
        "팀 업무 전체 흐름을 한눈에 볼 수 있는 기회",
        "업무 프로세스 재점검 계기 제공"
      ],
      "suggestions": [
        "R&D 특화 세부 실험 단계 입력 기능 추가",
        "기술적 변수와 연구 데이터 심층 입력 필드 개발",
        "실험 프로토콜별 맞춤형 워크플로우 템플릿 제공",
        "정량/정성 데이터 통합 대시보드 기능 구현"
      ],
      "wouldContinue": true,
      "emotionalState": "Cautiously Optimistic"
    },
    {
      "stageNumber": 5,
      "stageName": "업무 내용 입력",
      "actualMinutes": 12,
      "timePerception": "Too Short",
      "easeOfUse": 5,
      "clarity": 4,
      "value": 6,
      "painPoints": [
        "복잡한 실험 프로토콜의 세부 단계 입력 제한",
        "정량적/정성적 연구 데이터의 상세 캡처 어려움",
        "기술적 맥락과 연구 변수의 심층적 표현 부족",
        "다양한 실험 단계의 정밀한 워크플로우 매핑 미흡"
      ],
      "positivePoints": [
        "업무 구조화를 위한 기본 프레임워크 제공",
        "연구 프로세스의 시각화 가능성",
        "팀 업무 흐름에 대한 거시적 관점 확보"
      ],
      "suggestions": [
        "R&D 특화 세부 실험 단계 입력 기능 추가",
        "기술적 데이터 및 연구 변수의 다차원 입력 옵션 개발",
        "실험 프로토콜의 세부 워크플로우 매핑 기능 고도화",
        "연구 데이터의 정량/정성 분석 통합 대시보드 제공"
      ],
      "wouldContinue": true,
      "emotionalState": "Cautiously Optimistic"
    },
    {
      "stageNumber": 6,
      "stageName": "업무 추출 (AI)",
      "actualMinutes": 15,
      "timePerception": "Too Long",
      "easeOfUse": 4,
      "clarity": 3,
      "value": 5,
      "painPoints": [
        "복잡한 실험 프로토콜의 세부 단계 입력 제한",
        "기술적 연구 데이터의 정량적/정성적 특성 반영 부족",
        "다양한 연구 변수와 실험 단계의 심층적 캡처 미흡",
        "기술 개발 프로세스의 맥락적 깊이 부족"
      ],
      "positivePoints": [
        "업무 프로세스 시각화 시도",
        "팀 업무 구조화 가능성 제시",
        "디지털 워크플로우 매핑 초기 단계 접근"
      ],
      "suggestions": [
        "R&D 특화 세부 실험 단계 입력 기능 추가",
        "기술적 데이터 유형별 맞춤형 입력 템플릿 개발",
        "연구 변수의 다차원적 매핑 지원",
        "실험 프로토콜 세부 워크플로우 커스터마이징 기능"
      ],
      "wouldContinue": true,
      "emotionalState": "frustrated but curious"
    },
    {
      "stageNumber": 7,
      "stageName": "결과 요약",
      "actualMinutes": 12,
      "timePerception": "Too Short",
      "easeOfUse": 5,
      "clarity": 4,
      "value": 6,
      "painPoints": [
        "복잡한 실험 프로토콜의 세부 단계 캡처 제한",
        "기술적 연구 데이터의 정량적/정성적 특성 불충분한 반영",
        "연구 변수와 실험 단계의 심층적 캡처 미흡",
        "기술 개발 프로세스의 맥락적 깊이 부족"
      ],
      "positivePoints": [
        "업무 프로세스 시각화 기본 틀 제공",
        "대략적인 업무 흐름 이해에 도움",
        "팀 업무 구조화를 위한 초기 프레임워크 제시"
      ],
      "suggestions": [
        "R&D 특화된 세부 실험 단계 입력 기능 추가",
        "기술적 데이터 세부 입력 필드 확장",
        "연구 변수와 실험 프로토콜의 심층 매핑 기능 개발",
        "기술 개발 프로세스의 맥락적 깊이를 위한 전문 인터페이스 설계"
      ],
      "wouldContinue": true,
      "emotionalState": "약간 실망하지만 잠재력 인지"
    },
    {
      "stageNumber": 8,
      "stageName": "AI 교육",
      "actualMinutes": 12,
      "timePerception": "Too Short",
      "easeOfUse": 4,
      "clarity": 3,
      "value": 5,
      "painPoints": [
        "복잡한 실험 프로토콜의 세부 단계 캡처 불가능",
        "기술적 연구 데이터의 정량적/정성적 특성 심층 입력 제한",
        "다양한 연구 변수와 실험 단계의 맥락적 깊이 부족",
        "실험 결과와 기술 개발 프로세스의 상세 추적 어려움"
      ],
      "positivePoints": [
        "자동화 개념 학습에 대한 기본적인 인사이트 제공",
        "업무 프로세스 간소화 가능성 탐색",
        "팀 업무 구조화에 대한 초기 접근 기회"
      ],
      "suggestions": [
        "R&D 특화된 세부 실험 단계 입력 기능 추가",
        "기술적 데이터 유형별 맞춤형 입력 템플릿 개발",
        "연구 변수의 다차원적 매핑 기능 구현",
        "실험 프로토콜의 버전 관리 및 추적 시스템 통합"
      ],
      "wouldContinue": true,
      "emotionalState": "기대와 우려가 공존하는 상태"
    },
    {
      "stageNumber": 9,
      "stageName": "AI 컨설팅",
      "actualMinutes": 8,
      "timePerception": "Just Right",
      "easeOfUse": 4,
      "clarity": 3,
      "value": 5,
      "painPoints": [
        "복잡한 실험 프로토콜의 상세 단계 입력 제한",
        "기술적 연구 데이터의 정량적/정성적 특성 반영 미흡",
        "다양한 연구 변수와 실험 단계의 심층적 캡처 부족",
        "기술 개발 프로세스의 맥락적 깊이 부족"
      ],
      "positivePoints": [
        "대략적인 업무 구조화 가능",
        "자동화 잠재력 확인",
        "팀 프로세스 개선을 위한 초기 인사이트 제공"
      ],
      "suggestions": [
        "R&D 특화 세부 실험 단계 입력 기능 추가",
        "기술적 데이터 유형별 상세 입력 템플릿 개발",
        "연구 변수와 실험 프로토콜 맞춤형 매핑 기능 구현",
        "복잡한 기술 개발 프로세스 심층 분석 알고리즘 개발"
      ],
      "wouldContinue": true,
      "emotionalState": "기대와 우려가 공존하는 상태"
    },
    {
      "stageNumber": 10,
      "stageName": "워크플로우 설계",
      "actualMinutes": 15,
      "timePerception": "Too Long",
      "easeOfUse": 4,
      "clarity": 3,
      "value": 5,
      "painPoints": [
        "복잡한 실험 프로토콜의 상세 단계 입력 제한",
        "기술적 연구 데이터의 정량적/정성적 특성 심층 캡처 어려움",
        "연구 변수와 실험 단계의 맥락적 깊이 부족",
        "다양한 실험 변수의 세부적 매핑 미흡",
        "기술 개발 프로세스의 복잡성 반영 부족"
      ],
      "positivePoints": [
        "대략적인 업무 흐름 시각화 가능",
        "업무 프로세스에 대한 거시적 접근 제공",
        "팀 업무 구조화에 대한 초기 인사이트 제공"
      ],
      "suggestions": [
        "R&D 특화 세부 실험 단계 입력 기능 추가",
        "기술적 데이터 유형별 상세 입력 템플릿 개발",
        "연구 변수의 복잡성을 반영할 수 있는 고급 매핑 도구 개발",
        "실험 프로토콜의 비정형적 특성 반영 기능 추가",
        "기술 개발 단계의 정성적/정량적 데이터 심층 캡처 기능"
      ],
      "wouldContinue": true,
      "emotionalState": "frustrated but hopeful"
    },
    {
      "stageNumber": 11,
      "stageName": "최종 리포트",
      "actualMinutes": 7,
      "timePerception": "Just Right",
      "easeOfUse": 4,
      "clarity": 3,
      "value": 5,
      "painPoints": [
        "실험 프로토콜의 복잡한 단계를 제대로 캡처하지 못함",
        "기술적 세부사항의 깊이 있는 입력 제한",
        "연구 변수의 정량적/정성적 특성을 충분히 반영 못함",
        "다양한 실험 단계의 세부적인 워크플로우 매핑 미흡"
      ],
      "positivePoints": [
        "대략적인 업무 구조 시각화 가능",
        "팀 업무 프로세스에 대한 거시적 관점 제공",
        "업무 흐름의 초기 구조화 시도"
      ],
      "suggestions": [
        "R&D 특화 세부 실험 단계 입력 기능 추가",
        "기술적 변수와 연구 프로토콜의 심층 입력 인터페이스 개발",
        "정량적 데이터 세부 캡처 기능 강화",
        "실험 단계별 상세 워크플로우 매핑 도구 개발"
      ],
      "wouldContinue": true,
      "emotionalState": "약간 아쉽지만 잠재력 느낌"
    }
  ],
  "overallSatisfaction": 4.8,
  "wouldRecommend": false,
  "finalThoughts": "Expert 수준의 팀장으로서 전반적으로 개선이 필요한 교육 과정이라고 생각합니다. 실제 팀 업무에 적용할 수 있는 학습이었습니다.",
  "topImprovements": [
    "기술 연구 특화된 세부 워크플로우 템플릿 추가",
    "실험 단계별 상세 데이터 입력 기능 개발",
    "기술적 KPI와 연구 성과 추적 기능 고도화",
    "R&D 특화 워크플로우 템플릿 추가",
    "실험 단계별 세부 메트릭스 입력 기능"
  ]
}